[
  {
    "adigaram": "பயனில சொல்லாமை", 
    "couplet": [
      "பல்லார் முனியப் பயனில சொல்லுவான்", 
      "எல்லாரும் எள்ளப் படும்."
    ], 
    "explanation": [
      {
        "author": "Author-1", 
        "expln": "He who to the disgust of many speaks useless things will be despised by all."
      }, 
      {
        "author": "Translation", 
        "expln": "Words without sense, while chafe the wise,  Who babbles, him will all despise."
      }, 
      {
        "author": "திருக்குறளார் வீ. முனிசாமி", 
        "expln": "அறிவுடையார் பலரும் வெறுக்கும்படியாகப் பயனில்லாத சொற்களைப் பேசுகின்ற ஒருவன் எல்லா மக்களாலும் இகழப்படுவான்."
      }, 
      {
        "author": "மணக்குடவர்", 
        "expln": "பயனில்லாதவற்றைப் பலர் வெறுக்கச் சொல்லுபவன் எல்லாராலும் இகழப்படுவான்."
      }, 
      {
        "author": "பரிமேலழகர்", 
        "expln": "[அஃதாவது, தமக்கும் பிறர்க்கும் அறம் பொருள் இன்பம் ஆகிய பயன்களுள் ஒன்றும் பயவாத சொற்களைச் சொல்லாமை. பொய்,குறளை,கடுஞ்சொல்,பயனில் சொல் என வாக்கின்கண் நிகழும் பாவம் நான்கனுள், பொய் துறந்தார்க்கு அல்லது ஒருதலையாகக் கடியலாகாமையின், அஃது ஒழித்து இல்வாழ்வாரால் கடியப்படும் ஏனை மூன்றனுள் , கடுஞ்சொல் இனியவை கூறலானும் , குறளை புறங்கூறாமையானும் விலக்கி, நின்ற பயனில் சொல் இதனான் விலக்குகின்றார் ஆகலின், இது புறங்கூறாமையின் பின் வைக்கப்பட்டது.)  பல்லார் முனியப் பயன் இல சொல்லுவான் - அறிவுடையார் பலரும் கேட்டு வெறுப்பப் பயன் இலவாகிய சொற்களைச் சொல்லுவான், 'எல்லாரும் எள்ளப்படும்' - எல்லாரானும் இகழப்படும். (அறிவுடையார் பலரும் வெறுப்பவே, ஒழிந்தாரானும் இகழப்படுதலின், எல்லாரும் எள்ளப்படும் என்றார். மூன்றன் உருபு விகாரத்தால் தொக்கது.)."
      }, 
      {
        "author": "சாலமன் பாப்பையா", 
        "expln": "பலரும் கேட்டு வெறுக்கப், பயனற்ற சொற்களைச் சொல்லுபவன் எல்லாராலும் இகழப்படுவான்."
      }, 
      {
        "author": "மு.வரதராசனார்", 
        "expln": "கேட்டவர் பலரும் வெறுக்கும் படியாகப் பயனில்லாத சொற்களைச் சொல்லுகின்றவன், எல்லாராலும் இகழப்படுவான்."
      }
    ], 
    "inTamil": {
      "அதிகாரம்": "பயனில சொல்லாமை", 
      "உரை": [
        {
          "author": "Author-1", 
          "expln": "He who to the disgust of many speaks useless things will be despised by all."
        }, 
        {
          "author": "Translation", 
          "expln": "Words without sense, while chafe the wise,  Who babbles, him will all despise."
        }, 
        {
          "author": "திருக்குறளார் வீ. முனிசாமி", 
          "expln": "அறிவுடையார் பலரும் வெறுக்கும்படியாகப் பயனில்லாத சொற்களைப் பேசுகின்ற ஒருவன் எல்லா மக்களாலும் இகழப்படுவான்."
        }, 
        {
          "author": "மணக்குடவர்", 
          "expln": "பயனில்லாதவற்றைப் பலர் வெறுக்கச் சொல்லுபவன் எல்லாராலும் இகழப்படுவான்."
        }, 
        {
          "author": "பரிமேலழகர்", 
          "expln": "[அஃதாவது, தமக்கும் பிறர்க்கும் அறம் பொருள் இன்பம் ஆகிய பயன்களுள் ஒன்றும் பயவாத சொற்களைச் சொல்லாமை. பொய்,குறளை,கடுஞ்சொல்,பயனில் சொல் என வாக்கின்கண் நிகழும் பாவம் நான்கனுள், பொய் துறந்தார்க்கு அல்லது ஒருதலையாகக் கடியலாகாமையின், அஃது ஒழித்து இல்வாழ்வாரால் கடியப்படும் ஏனை மூன்றனுள் , கடுஞ்சொல் இனியவை கூறலானும் , குறளை புறங்கூறாமையானும் விலக்கி, நின்ற பயனில் சொல் இதனான் விலக்குகின்றார் ஆகலின், இது புறங்கூறாமையின் பின் வைக்கப்பட்டது.)  பல்லார் முனியப் பயன் இல சொல்லுவான் - அறிவுடையார் பலரும் கேட்டு வெறுப்பப் பயன் இலவாகிய சொற்களைச் சொல்லுவான், 'எல்லாரும் எள்ளப்படும்' - எல்லாரானும் இகழப்படும். (அறிவுடையார் பலரும் வெறுப்பவே, ஒழிந்தாரானும் இகழப்படுதலின், எல்லாரும் எள்ளப்படும் என்றார். மூன்றன் உருபு விகாரத்தால் தொக்கது.)."
        }, 
        {
          "author": "சாலமன் பாப்பையா", 
          "expln": "பலரும் கேட்டு வெறுக்கப், பயனற்ற சொற்களைச் சொல்லுபவன் எல்லாராலும் இகழப்படுவான்."
        }, 
        {
          "author": "மு.வரதராசனார்", 
          "expln": "கேட்டவர் பலரும் வெறுக்கும் படியாகப் பயனில்லாத சொற்களைச் சொல்லுகின்றவன், எல்லாராலும் இகழப்படுவான்."
        }
      ], 
      "குறள்": "பல்லார் முனியப் பயனில சொல்லுவான்  எல்லாரும் எள்ளப் படும்.", 
      "குறள்_பால்": "அறத்துப்பால்", 
      "குறள்_வரிசை": 191
    }, 
    "kural": "பல்லார் முனியப் பயனில சொல்லுவான்  எல்லாரும் எள்ளப் படும்.", 
    "kural_iyal": "இல்லறவியல்", 
    "kural_no": 191, 
    "kural_paal": "அறத்துப்பால்", 
    "tags": []
  }, 
  {
    "adigaram": "பயனில சொல்லாமை", 
    "couplet": [
      "பயனில பல்லார்முன் சொல்லல் நயனில", 
      "நட்டார்கண் செய்தலிற் றீது."
    ], 
    "explanation": [
      {
        "author": "Author-1", 
        "expln": "To speak useless things in the presence of many is a greater evil than to do unkind things towards friends."
      }, 
      {
        "author": "Translation", 
        "expln": "Words without sense, where many wise men hear, to pour  Than deeds to friends ungracious done offendeth more."
      }, 
      {
        "author": "திருக்குறளார் வீ. முனிசாமி", 
        "expln": "விரும்பத்  தகாத செயல்களை நண்பர்களிடம் செய்வதை விடப் பயனொன்றும் இல்லாத சொற்களை அறிவுடையார் பலர் முன்னே ஒருவன் சொல்லுதல் தீதானதாகும்."
      }, 
      {
        "author": "மணக்குடவர்", 
        "expln": "பயனில்லாத சொல்லைக் கொண்டாடுவானை மகனென்னாதொழிக; மக்களில் பதரென்று சொல்லுக, இது மக்கட் பண்பிலனென்றது."
      }, 
      {
        "author": "பரிமேலழகர்", 
        "expln": "பயன் இல பல்லார்முன் சொல்லல் - பயன் இலவாகிய சொற்களை அறிவுடையார் பலர் முன்பே ஒருவன் சொல்லுதல், நயன் இல நட்டார்கண் செய்தலின் தீது - விருப்பம் இலவாகிய செயல்களைத் தன் நட்டார் மாட்டுச் செய்தலினும் தீது. ('விருப்பமில' - வெறுப்பன. இச் சொல் அச்செயலினும் மிக இகழற்பாடு பயக்கும் என்பதாம்.)."
      }, 
      {
        "author": "சாலமன் பாப்பையா", 
        "expln": "ஒருவன் பலருக்கும் முன்னே பயனற்ற சொற்களைச் சொல்வது, நண்பர்களுக்குத் தீமை செய்வதைக் காட்டிலும் கொடியது."
      }, 
      {
        "author": "மு.வரதராசனார்", 
        "expln": "பலர் முன்னே பயனில்லாத சொற்களைச் சொல்லுதல், நண்பரிடத்தில் அறம் இல்லா செயல்களைச் செய்தலை விடத் தீமையானதாகும்."
      }
    ], 
    "inTamil": {
      "அதிகாரம்": "பயனில சொல்லாமை", 
      "உரை": [
        {
          "author": "Author-1", 
          "expln": "To speak useless things in the presence of many is a greater evil than to do unkind things towards friends."
        }, 
        {
          "author": "Translation", 
          "expln": "Words without sense, where many wise men hear, to pour  Than deeds to friends ungracious done offendeth more."
        }, 
        {
          "author": "திருக்குறளார் வீ. முனிசாமி", 
          "expln": "விரும்பத்  தகாத செயல்களை நண்பர்களிடம் செய்வதை விடப் பயனொன்றும் இல்லாத சொற்களை அறிவுடையார் பலர் முன்னே ஒருவன் சொல்லுதல் தீதானதாகும்."
        }, 
        {
          "author": "மணக்குடவர்", 
          "expln": "பயனில்லாத சொல்லைக் கொண்டாடுவானை மகனென்னாதொழிக; மக்களில் பதரென்று சொல்லுக, இது மக்கட் பண்பிலனென்றது."
        }, 
        {
          "author": "பரிமேலழகர்", 
          "expln": "பயன் இல பல்லார்முன் சொல்லல் - பயன் இலவாகிய சொற்களை அறிவுடையார் பலர் முன்பே ஒருவன் சொல்லுதல், நயன் இல நட்டார்கண் செய்தலின் தீது - விருப்பம் இலவாகிய செயல்களைத் தன் நட்டார் மாட்டுச் செய்தலினும் தீது. ('விருப்பமில' - வெறுப்பன. இச் சொல் அச்செயலினும் மிக இகழற்பாடு பயக்கும் என்பதாம்.)."
        }, 
        {
          "author": "சாலமன் பாப்பையா", 
          "expln": "ஒருவன் பலருக்கும் முன்னே பயனற்ற சொற்களைச் சொல்வது, நண்பர்களுக்குத் தீமை செய்வதைக் காட்டிலும் கொடியது."
        }, 
        {
          "author": "மு.வரதராசனார்", 
          "expln": "பலர் முன்னே பயனில்லாத சொற்களைச் சொல்லுதல், நண்பரிடத்தில் அறம் இல்லா செயல்களைச் செய்தலை விடத் தீமையானதாகும்."
        }
      ], 
      "குறள்": "பயனில பல்லார்முன் சொல்லல் நயனில  நட்டார்கண் செய்தலிற் றீது.", 
      "குறள்_பால்": "அறத்துப்பால்", 
      "குறள்_வரிசை": 192
    }, 
    "kural": "பயனில பல்லார்முன் சொல்லல் நயனில  நட்டார்கண் செய்தலிற் றீது.", 
    "kural_iyal": "இல்லறவியல்", 
    "kural_no": 192, 
    "kural_paal": "அறத்துப்பால்", 
    "tags": []
  }, 
  {
    "adigaram": "பயனில சொல்லாமை", 
    "couplet": [
      "நயனிலன் என்பது சொல்லும் பயனில", 
      "பாரித் துரைக்கும் உரை."
    ], 
    "explanation": [
      {
        "author": "Author-1", 
        "expln": "That conversation in which a man utters forth useless things will say of him 'he is without virtue'."
      }, 
      {
        "author": "Translation", 
        "expln": "Diffusive speech of useless words proclaims  A man who never righteous wisdom gains."
      }, 
      {
        "author": "திருக்குறளார் வீ. முனிசாமி", 
        "expln": "பயனொன்றும் இல்லாதவற்றை ஒருவன் விரிவுப்படுத்தி உரைக்கின்ற உரையானது அவன் நீதி இல்லாதவன் என்பதனைச் சொல்லிக் காட்டும்."
      }, 
      {
        "author": "மணக்குடவர்", 
        "expln": "நயனுடைய னல்லனென்பதனை யறிவிக்கும், பயனில்லாதவற்றைப் பரக்க விட்டுச் சொல்லுஞ் சொற்கள், இது பயனில சொல்வார் இம்மையின்கண் பிறரால் இயம்பப் படாரென்றது."
      }, 
      {
        "author": "பரிமேலழகர்", 
        "expln": "பயன் இல பாரித்து உரைக்கும் உரை - பயன் இலவாகிய பொருள்களை ஒருவன் விரித்து உரைக்கும் உரைதானே, நயன் இலன் என்பது சொல்லும் - இவன் நீதி இலன் என்பதனை உரைக்கும். (உரையால் இவன் 'நயனிலன்' என்பது அறியலாம் என்பார், அதனை உரைமேல் ஏற்றி, 'உரை சொல்லும்' என்றார்.)."
      }, 
      {
        "author": "சாலமன் பாப்பையா", 
        "expln": "பயனற்ற சொற்களை விரித்துப் பேசும் ஒருவன் பேச்சு அவன் நீதியற்றவன் என்பதைக் காட்டிவிடும்."
      }, 
      {
        "author": "மு.வரதராசனார்", 
        "expln": "ஒருவன் பயனில்லா பொருள்களைப் பற்றி விரிவாகச் சொல்லும் சொற்கள், அவன் அறம் இல்லாதவன் என்பதை அறிவிக்கும்."
      }
    ], 
    "inTamil": {
      "அதிகாரம்": "பயனில சொல்லாமை", 
      "உரை": [
        {
          "author": "Author-1", 
          "expln": "That conversation in which a man utters forth useless things will say of him 'he is without virtue'."
        }, 
        {
          "author": "Translation", 
          "expln": "Diffusive speech of useless words proclaims  A man who never righteous wisdom gains."
        }, 
        {
          "author": "திருக்குறளார் வீ. முனிசாமி", 
          "expln": "பயனொன்றும் இல்லாதவற்றை ஒருவன் விரிவுப்படுத்தி உரைக்கின்ற உரையானது அவன் நீதி இல்லாதவன் என்பதனைச் சொல்லிக் காட்டும்."
        }, 
        {
          "author": "மணக்குடவர்", 
          "expln": "நயனுடைய னல்லனென்பதனை யறிவிக்கும், பயனில்லாதவற்றைப் பரக்க விட்டுச் சொல்லுஞ் சொற்கள், இது பயனில சொல்வார் இம்மையின்கண் பிறரால் இயம்பப் படாரென்றது."
        }, 
        {
          "author": "பரிமேலழகர்", 
          "expln": "பயன் இல பாரித்து உரைக்கும் உரை - பயன் இலவாகிய பொருள்களை ஒருவன் விரித்து உரைக்கும் உரைதானே, நயன் இலன் என்பது சொல்லும் - இவன் நீதி இலன் என்பதனை உரைக்கும். (உரையால் இவன் 'நயனிலன்' என்பது அறியலாம் என்பார், அதனை உரைமேல் ஏற்றி, 'உரை சொல்லும்' என்றார்.)."
        }, 
        {
          "author": "சாலமன் பாப்பையா", 
          "expln": "பயனற்ற சொற்களை விரித்துப் பேசும் ஒருவன் பேச்சு அவன் நீதியற்றவன் என்பதைக் காட்டிவிடும்."
        }, 
        {
          "author": "மு.வரதராசனார்", 
          "expln": "ஒருவன் பயனில்லா பொருள்களைப் பற்றி விரிவாகச் சொல்லும் சொற்கள், அவன் அறம் இல்லாதவன் என்பதை அறிவிக்கும்."
        }
      ], 
      "குறள்": "நயனிலன் என்பது சொல்லும் பயனில  பாரித் துரைக்கும் உரை.", 
      "குறள்_பால்": "அறத்துப்பால்", 
      "குறள்_வரிசை": 193
    }, 
    "kural": "நயனிலன் என்பது சொல்லும் பயனில  பாரித் துரைக்கும் உரை.", 
    "kural_iyal": "இல்லறவியல்", 
    "kural_no": 193, 
    "kural_paal": "அறத்துப்பால்", 
    "tags": []
  }, 
  {
    "adigaram": "பயனில சொல்லாமை", 
    "couplet": [
      "நயன்சாரா நன்மையின் நீக்கும் பயன்சாராப்", 
      "பண்பில்சொல் பல்லா ரகத்து."
    ], 
    "explanation": [
      {
        "author": "Author-1", 
        "expln": "The words devoid of profit or pleasure which a man speaks will, being inconsistent with virtue, remove him from goodness."
      }, 
      {
        "author": "Translation", 
        "expln": "Unmeaning, worthless words, said to the multitude,  To none delight afford, and sever men from good."
      }, 
      {
        "author": "திருக்குறளார் வீ. முனிசாமி", 
        "expln": "நற்பயன் சேராத குணமில்லாத சொற்களைப் பலரிடத்திலும் ஒருவன் சொல்லுவானானால், அப்படிப் பட்டவனை, அவை நற்குணங்களிலிருந்து நீக்கிவிடும்."
      }, 
      {
        "author": "மணக்குடவர்", 
        "expln": "ஒருவன் ஒரு பயனைச் சாராத பண்பில்லாச் சொல்லைப் பலரிடத்துக் கூறுவானாயின் அவன் நடு சாராது நன்மையினீங்கும். இது விரும்பப்படாமையுமன்றி நன்மையும் பயவாதென்றது."
      }, 
      {
        "author": "பரிமேலழகர்", 
        "expln": "பயன் சாராப் பண்பு இல் சொல் பல்லார் அகத்து - பயனோடு படாத பண்புஇல் சொற்களை ஒருவன் பலரிடைச்சொல்லுமாயின், நயன் சாரா நன்மையின் நீக்கும் - அவை அவர்மாட்டு நீதியோடு படாவாய், அவனை நற்குணங்களின் நீக்கும். (பண்பு- இனிமையும், மெய்யும் முதலாய சொற்குணங்கள், 'சொல்லுமாயின்' என்பதும், 'அவர் மாட்டு' என்பதும், எச்சமாக வருவிக்கப்பட்டன.)."
      }, 
      {
        "author": "சாலமன் பாப்பையா", 
        "expln": "பயனற்ற, பண்பும் இல்லாத சொற்களை ஒருவன் பலரிடமும் சொன்னால் அச் சொற்களே அவனை நீதியுடன் சேராமல் நற்குணங்களிலிருந்து நீக்கிவிடும்."
      }, 
      {
        "author": "மு.வரதராசனார்", 
        "expln": "பயனோடு பொருந்தாத பண்பு இல்லாத சொற்களைப் பலரிடத்தும் சொல்லுதல், அறத்தோடு பொருந்தாமல் நன்மையிலிருந்து நீங்கச் செய்யும்."
      }
    ], 
    "inTamil": {
      "அதிகாரம்": "பயனில சொல்லாமை", 
      "உரை": [
        {
          "author": "Author-1", 
          "expln": "The words devoid of profit or pleasure which a man speaks will, being inconsistent with virtue, remove him from goodness."
        }, 
        {
          "author": "Translation", 
          "expln": "Unmeaning, worthless words, said to the multitude,  To none delight afford, and sever men from good."
        }, 
        {
          "author": "திருக்குறளார் வீ. முனிசாமி", 
          "expln": "நற்பயன் சேராத குணமில்லாத சொற்களைப் பலரிடத்திலும் ஒருவன் சொல்லுவானானால், அப்படிப் பட்டவனை, அவை நற்குணங்களிலிருந்து நீக்கிவிடும்."
        }, 
        {
          "author": "மணக்குடவர்", 
          "expln": "ஒருவன் ஒரு பயனைச் சாராத பண்பில்லாச் சொல்லைப் பலரிடத்துக் கூறுவானாயின் அவன் நடு சாராது நன்மையினீங்கும். இது விரும்பப்படாமையுமன்றி நன்மையும் பயவாதென்றது."
        }, 
        {
          "author": "பரிமேலழகர்", 
          "expln": "பயன் சாராப் பண்பு இல் சொல் பல்லார் அகத்து - பயனோடு படாத பண்புஇல் சொற்களை ஒருவன் பலரிடைச்சொல்லுமாயின், நயன் சாரா நன்மையின் நீக்கும் - அவை அவர்மாட்டு நீதியோடு படாவாய், அவனை நற்குணங்களின் நீக்கும். (பண்பு- இனிமையும், மெய்யும் முதலாய சொற்குணங்கள், 'சொல்லுமாயின்' என்பதும், 'அவர் மாட்டு' என்பதும், எச்சமாக வருவிக்கப்பட்டன.)."
        }, 
        {
          "author": "சாலமன் பாப்பையா", 
          "expln": "பயனற்ற, பண்பும் இல்லாத சொற்களை ஒருவன் பலரிடமும் சொன்னால் அச் சொற்களே அவனை நீதியுடன் சேராமல் நற்குணங்களிலிருந்து நீக்கிவிடும்."
        }, 
        {
          "author": "மு.வரதராசனார்", 
          "expln": "பயனோடு பொருந்தாத பண்பு இல்லாத சொற்களைப் பலரிடத்தும் சொல்லுதல், அறத்தோடு பொருந்தாமல் நன்மையிலிருந்து நீங்கச் செய்யும்."
        }
      ], 
      "குறள்": "நயன்சாரா நன்மையின் நீக்கும் பயன்சாராப்  பண்பில்சொல் பல்லா ரகத்து.", 
      "குறள்_பால்": "அறத்துப்பால்", 
      "குறள்_வரிசை": 194
    }, 
    "kural": "நயன்சாரா நன்மையின் நீக்கும் பயன்சாராப்  பண்பில்சொல் பல்லா ரகத்து.", 
    "kural_iyal": "இல்லறவியல்", 
    "kural_no": 194, 
    "kural_paal": "அறத்துப்பால்", 
    "tags": []
  }, 
  {
    "adigaram": "பயனில சொல்லாமை", 
    "couplet": [
      "சீர்மை சிறப்பொடு நீங்கும் பயனில", 
      "நீர்மை யுடையார் சொலின்."
    ], 
    "explanation": [
      {
        "author": "Author-1", 
        "expln": "If the good speak vain words their eminence and excellence will leave them."
      }, 
      {
        "author": "Translation", 
        "expln": "Gone are both fame and boasted excellence,  When men of worth speak of words devoid of sense."
      }, 
      {
        "author": "திருக்குறளார் வீ. முனிசாமி", 
        "expln": "நற்குணமுடைய இனிய தன்மை வாய்ந்த பெரியோர்கள், பயனில்லாத சொற்களைச் சொன்னால் அவர்களுடைய மேன்மையும் நன்மதிப்பும் நீங்கிவிடும்."
      }, 
      {
        "author": "மணக்குடவர்", 
        "expln": "பயனில்லாதவற்றை நீர்மையுடையார் கூறுவாராயின் அவர்க்கு உண்டான சீர்மையும் சிறப்பும் போம் இது நீர்மையுடையா ராயினும் எல்லா நன்மையும் போமென்றது."
      }, 
      {
        "author": "பரிமேலழகர்", 
        "expln": "பயன் இல நீர்மையுடையார் சொலின் - பயன் இலவாகிய சொற்களை இனிய நீர்மையுடையார் சொல்லுவாராயின், சீர்மை சிறப்பொடு நீங்கும் - அவரது விழுப்பமும் அதனால் வரும் நன்கு மதிக்கற்பாடும் உடனே நீங்கும். (நீர்மை: நீரின் தன்மை. 'சொலின்' என்பது சொல்லாமையை விளக்கிற்று.)."
      }, 
      {
        "author": "சாலமன் பாப்பையா", 
        "expln": "இனிய குணத்தவர் பயனற்ற சொற்களைச் சொன்னால், அவர் பெருமையும், புகழும் அப்பொழுதே நீங்கிவிடும்."
      }, 
      {
        "author": "மு.வரதராசனார்", 
        "expln": "பயனில்லாத சொற்களை நல்ல பண்பு உடையவர் சொல்லுவாரானால், அவனுடைய மேம்பாடு அவர்க்குரிய மதிப்போடு நீங்கிவிடும்."
      }
    ], 
    "inTamil": {
      "அதிகாரம்": "பயனில சொல்லாமை", 
      "உரை": [
        {
          "author": "Author-1", 
          "expln": "If the good speak vain words their eminence and excellence will leave them."
        }, 
        {
          "author": "Translation", 
          "expln": "Gone are both fame and boasted excellence,  When men of worth speak of words devoid of sense."
        }, 
        {
          "author": "திருக்குறளார் வீ. முனிசாமி", 
          "expln": "நற்குணமுடைய இனிய தன்மை வாய்ந்த பெரியோர்கள், பயனில்லாத சொற்களைச் சொன்னால் அவர்களுடைய மேன்மையும் நன்மதிப்பும் நீங்கிவிடும்."
        }, 
        {
          "author": "மணக்குடவர்", 
          "expln": "பயனில்லாதவற்றை நீர்மையுடையார் கூறுவாராயின் அவர்க்கு உண்டான சீர்மையும் சிறப்பும் போம் இது நீர்மையுடையா ராயினும் எல்லா நன்மையும் போமென்றது."
        }, 
        {
          "author": "பரிமேலழகர்", 
          "expln": "பயன் இல நீர்மையுடையார் சொலின் - பயன் இலவாகிய சொற்களை இனிய நீர்மையுடையார் சொல்லுவாராயின், சீர்மை சிறப்பொடு நீங்கும் - அவரது விழுப்பமும் அதனால் வரும் நன்கு மதிக்கற்பாடும் உடனே நீங்கும். (நீர்மை: நீரின் தன்மை. 'சொலின்' என்பது சொல்லாமையை விளக்கிற்று.)."
        }, 
        {
          "author": "சாலமன் பாப்பையா", 
          "expln": "இனிய குணத்தவர் பயனற்ற சொற்களைச் சொன்னால், அவர் பெருமையும், புகழும் அப்பொழுதே நீங்கிவிடும்."
        }, 
        {
          "author": "மு.வரதராசனார்", 
          "expln": "பயனில்லாத சொற்களை நல்ல பண்பு உடையவர் சொல்லுவாரானால், அவனுடைய மேம்பாடு அவர்க்குரிய மதிப்போடு நீங்கிவிடும்."
        }
      ], 
      "குறள்": "சீர்மை சிறப்பொடு நீங்கும் பயனில  நீர்மை யுடையார் சொலின்.", 
      "குறள்_பால்": "அறத்துப்பால்", 
      "குறள்_வரிசை": 195
    }, 
    "kural": "சீர்மை சிறப்பொடு நீங்கும் பயனில  நீர்மை யுடையார் சொலின்.", 
    "kural_iyal": "இல்லறவியல்", 
    "kural_no": 195, 
    "kural_paal": "அறத்துப்பால்", 
    "tags": []
  }, 
  {
    "adigaram": "பயனில சொல்லாமை", 
    "couplet": [
      "பயனில்சொல் பராட்டு வானை மகன்எனல்", 
      "மக்கட் பதடி யெனல்."
    ], 
    "explanation": [
      {
        "author": "Author-1", 
        "expln": "Call not him a man who parades forth his empty words. Call him the chaff of men."
      }, 
      {
        "author": "Translation", 
        "expln": "Who makes display of idle words' inanity,  Call him not man, -chaff of humanity!."
      }, 
      {
        "author": "திருக்குறளார் வீ. முனிசாமி", 
        "expln": "பயனில்லாத சொற்களைப் பலகாலும் பாராட்டிப் பேசுபவனை மனிதன் என்று கூறாதே; மக்களுக்குள்ளே பதர் என்று சொல்லுக."
      }, 
      {
        "author": "மணக்குடவர்", 
        "expln": "பயனில்லாதவற்றைப் பலர் முன்பு கூறுதல், விருப்பமில்லாதவற்றை நட்டார் மாட்டுச் செய்தலினுந் தீதே, இது பயனில சொல்லல் இம்மை மறுமை யிரண்டின் கண்ணுந் தீமை பயக்கு மென்றது."
      }, 
      {
        "author": "பரிமேலழகர்", 
        "expln": "பயன்இல்சொல் பாராட்டுவானை மகன் எனல் - பயன் இல்லாத சொற்களைப் பலகாலுஞ் சொல்லுவானை மகன் என்று சொல்லற்க, மக்கட் பதடி எனல் - மக்களுள் பதர் என்று சொல்லுக. (அல் விகுதி வியங்கோள், முன் எதிர்மறையினும், பின் உடன்பாட்டினும் வந்தது. அறிவு என்னும் உள்ளீடு இன்மையின், 'மக்கள் பதடி' என்றார். இவை ஆறு பாட்டானும் பயன் இல்லாத சொற்களைச் சொல்லுதலின் குற்றம் கூறப்பட்டது.)."
      }, 
      {
        "author": "சாலமன் பாப்பையா", 
        "expln": "பயனற்ற சொற்களையே பலகாலமும் சொல்பவனை மனிதன் என வேண்டா; மனிதருள் பதர் என்றே சொல்லுங்கள்."
      }, 
      {
        "author": "மு.வரதராசனார்", 
        "expln": "பயனில்லாத சொற்களைப் பலமுறையும் சொல்லுகின்ற ஒருவனை மனிதன் என்று சொல்லக்கூடாது, மக்களுள் பதர் என்று சொல்லவேண்டும்."
      }
    ], 
    "inTamil": {
      "அதிகாரம்": "பயனில சொல்லாமை", 
      "உரை": [
        {
          "author": "Author-1", 
          "expln": "Call not him a man who parades forth his empty words. Call him the chaff of men."
        }, 
        {
          "author": "Translation", 
          "expln": "Who makes display of idle words' inanity,  Call him not man, -chaff of humanity!."
        }, 
        {
          "author": "திருக்குறளார் வீ. முனிசாமி", 
          "expln": "பயனில்லாத சொற்களைப் பலகாலும் பாராட்டிப் பேசுபவனை மனிதன் என்று கூறாதே; மக்களுக்குள்ளே பதர் என்று சொல்லுக."
        }, 
        {
          "author": "மணக்குடவர்", 
          "expln": "பயனில்லாதவற்றைப் பலர் முன்பு கூறுதல், விருப்பமில்லாதவற்றை நட்டார் மாட்டுச் செய்தலினுந் தீதே, இது பயனில சொல்லல் இம்மை மறுமை யிரண்டின் கண்ணுந் தீமை பயக்கு மென்றது."
        }, 
        {
          "author": "பரிமேலழகர்", 
          "expln": "பயன்இல்சொல் பாராட்டுவானை மகன் எனல் - பயன் இல்லாத சொற்களைப் பலகாலுஞ் சொல்லுவானை மகன் என்று சொல்லற்க, மக்கட் பதடி எனல் - மக்களுள் பதர் என்று சொல்லுக. (அல் விகுதி வியங்கோள், முன் எதிர்மறையினும், பின் உடன்பாட்டினும் வந்தது. அறிவு என்னும் உள்ளீடு இன்மையின், 'மக்கள் பதடி' என்றார். இவை ஆறு பாட்டானும் பயன் இல்லாத சொற்களைச் சொல்லுதலின் குற்றம் கூறப்பட்டது.)."
        }, 
        {
          "author": "சாலமன் பாப்பையா", 
          "expln": "பயனற்ற சொற்களையே பலகாலமும் சொல்பவனை மனிதன் என வேண்டா; மனிதருள் பதர் என்றே சொல்லுங்கள்."
        }, 
        {
          "author": "மு.வரதராசனார்", 
          "expln": "பயனில்லாத சொற்களைப் பலமுறையும் சொல்லுகின்ற ஒருவனை மனிதன் என்று சொல்லக்கூடாது, மக்களுள் பதர் என்று சொல்லவேண்டும்."
        }
      ], 
      "குறள்": "பயனில்சொல் பராட்டு வானை மகன்எனல் மக்கட் பதடி யெனல்.", 
      "குறள்_பால்": "அறத்துப்பால்", 
      "குறள்_வரிசை": 196
    }, 
    "kural": "பயனில்சொல் பராட்டு வானை மகன்எனல் மக்கட் பதடி யெனல்.", 
    "kural_iyal": "இல்லறவியல்", 
    "kural_no": 196, 
    "kural_paal": "அறத்துப்பால்", 
    "tags": []
  }, 
  {
    "adigaram": "பயனில சொல்லாமை", 
    "couplet": [
      "நயனில சொல்லினுஞ் சொல்லுக சான்றோர்", 
      "பயனில சொல்லாமை நன்று."
    ], 
    "explanation": [
      {
        "author": "Author-1", 
        "expln": "Let the wise if they will, speak things without excellence; it will be well for them not to speak useless things."
      }, 
      {
        "author": "Translation", 
        "expln": "Let those who list speak things that no delight afford,  'Tis good for men of worth to speak no idle word."
      }, 
      {
        "author": "திருக்குறளார் வீ. முனிசாமி", 
        "expln": "சான்றோர்கள், நயமில்லாத சொற்களைச் சொன்னாலும் சொல்லுவார்களாக; பயனில்லாத சொற்களைச் சொல்லாதிருத்தல் நல்லதாகும்."
      }, 
      {
        "author": "மணக்குடவர்", 
        "expln": "சான்றோர் நயனில்லாதவற்றைச் சொல்லினுஞ் சொல்லுக, அமையும்; பயனில்லாதவற்றைச் சொல்லாமை நன்று. இது சான்றோர்க்கு ஆகாதென்றது."
      }, 
      {
        "author": "பரிமேலழகர்", 
        "expln": "நயன் இல சான்றோர் சொல்லினும் சொல்லுக - சான்றோர் நீதியோடு படாத சொற்களைச் சொன்னாராயினும் அஃது அமையும், பயன் இல சொல்லாமை நன்று - அவர் பயன் இலவற்றைச் சொல்லாமை பெறின், அது நன்று ('சொல்லினும்' எனவே, சொல்லாமை பெறப்பட்டது. நயன் இலவற்றினும் பயன் இல தீய என்பதாம்.)."
      }, 
      {
        "author": "சாலமன் பாப்பையா", 
        "expln": "நீதியற்ற சொற்களைச் சொன்னாலும் பயனற்ற சொற்களைச் சொல்லாமல் இருப்பது சான்றோர்க்கு நல்லது."
      }, 
      {
        "author": "மு.வரதராசனார்", 
        "expln": "அறம் இல்லாதவற்றைச் சொன்னாலும் சொல்லலாம், சான்றோர் பயன் இல்லாத சொற்களைச் சொல்லாமல் இருத்தல் நன்மையாகும்."
      }
    ], 
    "inTamil": {
      "அதிகாரம்": "பயனில சொல்லாமை", 
      "உரை": [
        {
          "author": "Author-1", 
          "expln": "Let the wise if they will, speak things without excellence; it will be well for them not to speak useless things."
        }, 
        {
          "author": "Translation", 
          "expln": "Let those who list speak things that no delight afford,  'Tis good for men of worth to speak no idle word."
        }, 
        {
          "author": "திருக்குறளார் வீ. முனிசாமி", 
          "expln": "சான்றோர்கள், நயமில்லாத சொற்களைச் சொன்னாலும் சொல்லுவார்களாக; பயனில்லாத சொற்களைச் சொல்லாதிருத்தல் நல்லதாகும்."
        }, 
        {
          "author": "மணக்குடவர்", 
          "expln": "சான்றோர் நயனில்லாதவற்றைச் சொல்லினுஞ் சொல்லுக, அமையும்; பயனில்லாதவற்றைச் சொல்லாமை நன்று. இது சான்றோர்க்கு ஆகாதென்றது."
        }, 
        {
          "author": "பரிமேலழகர்", 
          "expln": "நயன் இல சான்றோர் சொல்லினும் சொல்லுக - சான்றோர் நீதியோடு படாத சொற்களைச் சொன்னாராயினும் அஃது அமையும், பயன் இல சொல்லாமை நன்று - அவர் பயன் இலவற்றைச் சொல்லாமை பெறின், அது நன்று ('சொல்லினும்' எனவே, சொல்லாமை பெறப்பட்டது. நயன் இலவற்றினும் பயன் இல தீய என்பதாம்.)."
        }, 
        {
          "author": "சாலமன் பாப்பையா", 
          "expln": "நீதியற்ற சொற்களைச் சொன்னாலும் பயனற்ற சொற்களைச் சொல்லாமல் இருப்பது சான்றோர்க்கு நல்லது."
        }, 
        {
          "author": "மு.வரதராசனார்", 
          "expln": "அறம் இல்லாதவற்றைச் சொன்னாலும் சொல்லலாம், சான்றோர் பயன் இல்லாத சொற்களைச் சொல்லாமல் இருத்தல் நன்மையாகும்."
        }
      ], 
      "குறள்": "நயனில சொல்லினுஞ் சொல்லுக சான்றோர்  பயனில சொல்லாமை நன்று.", 
      "குறள்_பால்": "அறத்துப்பால்", 
      "குறள்_வரிசை": 197
    }, 
    "kural": "நயனில சொல்லினுஞ் சொல்லுக சான்றோர்  பயனில சொல்லாமை நன்று.", 
    "kural_iyal": "இல்லறவியல்", 
    "kural_no": 197, 
    "kural_paal": "அறத்துப்பால்", 
    "tags": []
  }, 
  {
    "adigaram": "பயனில சொல்லாமை", 
    "couplet": [
      "அரும்பயன் ஆயும் அறிவினார் சொல்லார்", 
      "பெரும்பயன் இல்லாத சொல்."
    ], 
    "explanation": [
      {
        "author": "Author-1", 
        "expln": "The wise who seek after rare pleasures will not speak words that have not much weight in them."
      }, 
      {
        "author": "Translation", 
        "expln": "The wise who weigh the worth of every utterance,  Speak none but words of deep significance."
      }, 
      {
        "author": "திருக்குறளார் வீ. முனிசாமி", 
        "expln": "அறிதற்கரிய நற்பயன்களை ஆய்ந்தறியும் அறிவுடையவர்கள், மிக்க பயனில்லாத சொற்களைச் சொல்ல மாட்டார்கள்."
      }, 
      {
        "author": "மணக்குடவர்", 
        "expln": "அரிய பொருளை யாராயும் அறிவினையுடையார் சொல்லார்; பெரிய பயனில்லாத சொற்களை, இது மேற்கூறிய குற்றமெல்லாம் பயத்தலின் இதனை யறிவுடையார் கூறாரென்றது."
      }, 
      {
        "author": "பரிமேலழகர்", 
        "expln": "அரும்பயன் ஆயும் அறிவினார் - அறிதற்கு அரிய பயன்களை ஆராயவல்ல அறிவினையுடையார், பெரும்பயன் இல்லாத சொல் சொல்லார் - மிக்க பயனுடைய அல்லாத சொற்களைச் சொல்லார். (அறிதற்கு அரிய பயன்களாவன, வீடு பேறும், மேற்கதிச் செலவும் முதலாயின. 'பெரும்பயன் இல்லாத' எனவே பயன் சிறிது உடையனவும் ஒழிக்கப்பட்டன.)."
      }, 
      {
        "author": "சாலமன் பாப்பையா", 
        "expln": "அரிய பயன்களை ஆராயும் அறிவுடையோர், பெரும்பயன் இல்லாத சொற்களைச் சொல்வார்."
      }, 
      {
        "author": "மு.வரதராசனார்", 
        "expln": "அருமையான பயன்களை ஆராயவல்ல அறிவை உடைய அறிஞர், மிக்க பயன் இல்லாத சொற்களை ஒருபோதும் சொல்லமாட்டார்."
      }
    ], 
    "inTamil": {
      "அதிகாரம்": "பயனில சொல்லாமை", 
      "உரை": [
        {
          "author": "Author-1", 
          "expln": "The wise who seek after rare pleasures will not speak words that have not much weight in them."
        }, 
        {
          "author": "Translation", 
          "expln": "The wise who weigh the worth of every utterance,  Speak none but words of deep significance."
        }, 
        {
          "author": "திருக்குறளார் வீ. முனிசாமி", 
          "expln": "அறிதற்கரிய நற்பயன்களை ஆய்ந்தறியும் அறிவுடையவர்கள், மிக்க பயனில்லாத சொற்களைச் சொல்ல மாட்டார்கள்."
        }, 
        {
          "author": "மணக்குடவர்", 
          "expln": "அரிய பொருளை யாராயும் அறிவினையுடையார் சொல்லார்; பெரிய பயனில்லாத சொற்களை, இது மேற்கூறிய குற்றமெல்லாம் பயத்தலின் இதனை யறிவுடையார் கூறாரென்றது."
        }, 
        {
          "author": "பரிமேலழகர்", 
          "expln": "அரும்பயன் ஆயும் அறிவினார் - அறிதற்கு அரிய பயன்களை ஆராயவல்ல அறிவினையுடையார், பெரும்பயன் இல்லாத சொல் சொல்லார் - மிக்க பயனுடைய அல்லாத சொற்களைச் சொல்லார். (அறிதற்கு அரிய பயன்களாவன, வீடு பேறும், மேற்கதிச் செலவும் முதலாயின. 'பெரும்பயன் இல்லாத' எனவே பயன் சிறிது உடையனவும் ஒழிக்கப்பட்டன.)."
        }, 
        {
          "author": "சாலமன் பாப்பையா", 
          "expln": "அரிய பயன்களை ஆராயும் அறிவுடையோர், பெரும்பயன் இல்லாத சொற்களைச் சொல்வார்."
        }, 
        {
          "author": "மு.வரதராசனார்", 
          "expln": "அருமையான பயன்களை ஆராயவல்ல அறிவை உடைய அறிஞர், மிக்க பயன் இல்லாத சொற்களை ஒருபோதும் சொல்லமாட்டார்."
        }
      ], 
      "குறள்": "அரும்பயன் ஆயும் அறிவினார் சொல்லார்  பெரும்பயன் இல்லாத சொல்.", 
      "குறள்_பால்": "அறத்துப்பால்", 
      "குறள்_வரிசை": 198
    }, 
    "kural": "அரும்பயன் ஆயும் அறிவினார் சொல்லார்  பெரும்பயன் இல்லாத சொல்.", 
    "kural_iyal": "இல்லறவியல்", 
    "kural_no": 198, 
    "kural_paal": "அறத்துப்பால்", 
    "tags": []
  }, 
  {
    "adigaram": "பயனில சொல்லாமை", 
    "couplet": [
      "பொருள்தீர்ந்த பொச்சாந்துஞ் சொல்லார் மருள்தீர்ந்த", 
      "மாசறு காட்சி யவர்."
    ], 
    "explanation": [
      {
        "author": "Author-1", 
        "expln": "Those wise men who are without faults and are freed from ignorance will not even forgetfully speak things that profit not."
      }, 
      {
        "author": "Translation", 
        "expln": "The men of vision pure, from wildering folly free,  Not e'en in thoughtless hour, speak words of vanity."
      }, 
      {
        "author": "திருக்குறளார் வீ. முனிசாமி", 
        "expln": "அஞ்ஞானத்திலிருந்து நீங்கிய தூய அறிவினையுடைய பெரியோர்கள், பயனில்லாத சொற்களை மறந்தும் சொல்லமாட்டார்கள்."
      }, 
      {
        "author": "மணக்குடவர்", 
        "expln": "பொருளில்லாத சொல்லை மறந்துஞ் சொல்லார்; மயக்கந் தீர்ந்த குற்றமற்ற தெளிவினை யுடையார், இது தெளிவுடையார் கூறாரென்றது."
      }, 
      {
        "author": "பரிமேலழகர்", 
        "expln": "பொருள் தீர்ந்த பொச்சாந்தும் சொல்லார் - பயனின் நீங்கிய சொற்களை மறந்தும் சொல்லார், 'மருள் தீர்ந்த' மாசுஅறு காட்சியவர் - மயக்கத்தின் நீங்கிய தூய அறிவினையுடையார். '('தூய அறிவு' மெய்யறிவு. 'மருள் தீர்ந்த' என்னும் பெயரெச்சம் காட்சியவர் என்னும் குறிப்புப்பெயர் கொண்டது. இவை மூன்று பாட்டானும் பயன்இல சொல்லாமையின் குணம் கூறப்பட்டது)."
      }, 
      {
        "author": "சாலமன் பாப்பையா", 
        "expln": "மயக்கமற்ற தூய அறிவினை உடையவர், பொருளற்ற சொற்களை மறந்தும் சொல்லார்."
      }, 
      {
        "author": "மு.வரதராசனார்", 
        "expln": "மயக்கத்திலிருந்து தெளிந்த மாசற்ற அறிவை உடையவர், பயன் நீங்கிய சொற்களை ஒருகால் மறந்தும் சொல்லமாட்டார்."
      }
    ], 
    "inTamil": {
      "அதிகாரம்": "பயனில சொல்லாமை", 
      "உரை": [
        {
          "author": "Author-1", 
          "expln": "Those wise men who are without faults and are freed from ignorance will not even forgetfully speak things that profit not."
        }, 
        {
          "author": "Translation", 
          "expln": "The men of vision pure, from wildering folly free,  Not e'en in thoughtless hour, speak words of vanity."
        }, 
        {
          "author": "திருக்குறளார் வீ. முனிசாமி", 
          "expln": "அஞ்ஞானத்திலிருந்து நீங்கிய தூய அறிவினையுடைய பெரியோர்கள், பயனில்லாத சொற்களை மறந்தும் சொல்லமாட்டார்கள்."
        }, 
        {
          "author": "மணக்குடவர்", 
          "expln": "பொருளில்லாத சொல்லை மறந்துஞ் சொல்லார்; மயக்கந் தீர்ந்த குற்றமற்ற தெளிவினை யுடையார், இது தெளிவுடையார் கூறாரென்றது."
        }, 
        {
          "author": "பரிமேலழகர்", 
          "expln": "பொருள் தீர்ந்த பொச்சாந்தும் சொல்லார் - பயனின் நீங்கிய சொற்களை மறந்தும் சொல்லார், 'மருள் தீர்ந்த' மாசுஅறு காட்சியவர் - மயக்கத்தின் நீங்கிய தூய அறிவினையுடையார். '('தூய அறிவு' மெய்யறிவு. 'மருள் தீர்ந்த' என்னும் பெயரெச்சம் காட்சியவர் என்னும் குறிப்புப்பெயர் கொண்டது. இவை மூன்று பாட்டானும் பயன்இல சொல்லாமையின் குணம் கூறப்பட்டது)."
        }, 
        {
          "author": "சாலமன் பாப்பையா", 
          "expln": "மயக்கமற்ற தூய அறிவினை உடையவர், பொருளற்ற சொற்களை மறந்தும் சொல்லார்."
        }, 
        {
          "author": "மு.வரதராசனார்", 
          "expln": "மயக்கத்திலிருந்து தெளிந்த மாசற்ற அறிவை உடையவர், பயன் நீங்கிய சொற்களை ஒருகால் மறந்தும் சொல்லமாட்டார்."
        }
      ], 
      "குறள்": "பொருள்தீர்ந்த பொச்சாந்துஞ் சொல்லார் மருள்தீர்ந்த  மாசறு காட்சி யவர்.", 
      "குறள்_பால்": "அறத்துப்பால்", 
      "குறள்_வரிசை": 199
    }, 
    "kural": "பொருள்தீர்ந்த பொச்சாந்துஞ் சொல்லார் மருள்தீர்ந்த  மாசறு காட்சி யவர்.", 
    "kural_iyal": "இல்லறவியல்", 
    "kural_no": 199, 
    "kural_paal": "அறத்துப்பால்", 
    "tags": []
  }, 
  {
    "adigaram": "பயனில சொல்லாமை", 
    "couplet": [
      "சொல்லுக சொல்லிற் பயனுடைய சொல்லற்க", 
      "சொல்லிற் பயனிலாச் சொல்."
    ], 
    "explanation": [
      {
        "author": "Author-1", 
        "expln": "Speak what is useful, and speak not useless words."
      }, 
      {
        "author": "Translation", 
        "expln": "If speak you will, speak words that fruit afford,  If speak you will, speak never fruitless word."
      }, 
      {
        "author": "திருக்குறளார் வீ. முனிசாமி", 
        "expln": "சொற்கள் பலவற்றுள்ளும் பயன்தரக்கூடிய சொற்களைச் சொல்லுவாயாக; சொற்களில் பயனேதும் இல்லாத சொற்களைச் சொல்லாதிருப்பாயாக."
      }, 
      {
        "author": "மணக்குடவர்", 
        "expln": "சொல்லுவனாயின் பயனுடைய சொற்களைச் சொல்லுக: சொற்களிற் பயனில்லாத சொற்களைச் சொல்லா தொழிக. இது பயனில சொல்லாமை வேண்டுமென்றது."
      }, 
      {
        "author": "பரிமேலழகர்", 
        "expln": "சொல்லில் பயன் உடைய சொல்லுக - சொற்களில் பயன் உடைய சொற்களைச் சொல்லுக, சொல்லில் பயனில்லாச் சொல் சொல்லற்க - சொற்களில் பயன் இல்லாத சொற்களைச் சொல்லாது ஒழிக. ('சொல்லில்' என்பது இருவழியும் மிகையாயினும், சொற் பொருட் பின்வருநிலை என்னும் அணி நோக்கி வந்தது. 'வைகலும் வைகல் வரக்கண்டும்' (நாலடி 39) என்பது போல. இதனால் சொல்லப்படுவனவும் படாதனவும் நியமிக்கப்பட்டன.)."
      }, 
      {
        "author": "சாலமன் பாப்பையா", 
        "expln": "சொற்களில் அறம், பொருள், இன்பம் ஆகிய பயன்தரும் சொற்களையே சொல்லுக; பயனற்ற சொற்களைச் சொல்லவேண்டா."
      }, 
      {
        "author": "மு.வரதராசனார்", 
        "expln": "சொற்களில் பயன் உடைய சொற்களை மட்டுமே சொல்லவேண்டும், பயன் இல்லாதவைகளாகிய சொற்களை சொல்லவே கூடாது."
      }
    ], 
    "inTamil": {
      "அதிகாரம்": "பயனில சொல்லாமை", 
      "உரை": [
        {
          "author": "Author-1", 
          "expln": "Speak what is useful, and speak not useless words."
        }, 
        {
          "author": "Translation", 
          "expln": "If speak you will, speak words that fruit afford,  If speak you will, speak never fruitless word."
        }, 
        {
          "author": "திருக்குறளார் வீ. முனிசாமி", 
          "expln": "சொற்கள் பலவற்றுள்ளும் பயன்தரக்கூடிய சொற்களைச் சொல்லுவாயாக; சொற்களில் பயனேதும் இல்லாத சொற்களைச் சொல்லாதிருப்பாயாக."
        }, 
        {
          "author": "மணக்குடவர்", 
          "expln": "சொல்லுவனாயின் பயனுடைய சொற்களைச் சொல்லுக: சொற்களிற் பயனில்லாத சொற்களைச் சொல்லா தொழிக. இது பயனில சொல்லாமை வேண்டுமென்றது."
        }, 
        {
          "author": "பரிமேலழகர்", 
          "expln": "சொல்லில் பயன் உடைய சொல்லுக - சொற்களில் பயன் உடைய சொற்களைச் சொல்லுக, சொல்லில் பயனில்லாச் சொல் சொல்லற்க - சொற்களில் பயன் இல்லாத சொற்களைச் சொல்லாது ஒழிக. ('சொல்லில்' என்பது இருவழியும் மிகையாயினும், சொற் பொருட் பின்வருநிலை என்னும் அணி நோக்கி வந்தது. 'வைகலும் வைகல் வரக்கண்டும்' (நாலடி 39) என்பது போல. இதனால் சொல்லப்படுவனவும் படாதனவும் நியமிக்கப்பட்டன.)."
        }, 
        {
          "author": "சாலமன் பாப்பையா", 
          "expln": "சொற்களில் அறம், பொருள், இன்பம் ஆகிய பயன்தரும் சொற்களையே சொல்லுக; பயனற்ற சொற்களைச் சொல்லவேண்டா."
        }, 
        {
          "author": "மு.வரதராசனார்", 
          "expln": "சொற்களில் பயன் உடைய சொற்களை மட்டுமே சொல்லவேண்டும், பயன் இல்லாதவைகளாகிய சொற்களை சொல்லவே கூடாது."
        }
      ], 
      "குறள்": "சொல்லுக சொல்லிற் பயனுடைய சொல்லற்க  சொல்லிற் பயனிலாச் சொல்.", 
      "குறள்_பால்": "அறத்துப்பால்", 
      "குறள்_வரிசை": 200
    }, 
    "kural": "சொல்லுக சொல்லிற் பயனுடைய சொல்லற்க  சொல்லிற் பயனிலாச் சொல்.", 
    "kural_iyal": "இல்லறவியல்", 
    "kural_no": 200, 
    "kural_paal": "அறத்துப்பால்", 
    "tags": []
  }
]